connector/__init__.py
connector/fetch.py
connector/ind.py
connector/requests.py
sqlconnectphp-0.4.dist-info/LICENSE.txt
sqlconnectphp-0.4.dist-info/METADATA
sqlconnectphp-0.4.dist-info/WHEEL
sqlconnectphp-0.4.dist-info/top_level.txt
sqlconnectphp-0.4.dist-info/RECORD
