Metadata-Version: 2.1
Name: sqlconnectphp
Version: 0.4
Summary: basic crypto package
Author: ctgroup
Author-email: babuc4163@gmail.com
Classifier: Programming Language :: Python :: 3
Classifier: License :: OSI Approved :: MIT License
Classifier: Operating System :: OS Independent
License-File: LICENSE.txt
